examples/__init__.py
examples/simple_flow.py
examples/simple_sourcing.py
mlfastflow/FastKNN.py
mlfastflow/Sourcing.py
mlfastflow/__init__.py
mlfastflow/bigqueryclient.py
mlfastflow/bigqueryclientpolars.py
mlfastflow/core.py
mlfastflow/utils.py
mlfastflow-0.2.8.7.dist-info/licenses/LICENSE
tests/__init__.py
tests/local_test_bigqueryclient.py
tests/pypi_test_bigqueryclient.py
tests/test_bigquery_performance.py
tests/test_core.py
tests/test_utils.py
mlfastflow-0.2.8.7.dist-info/METADATA
mlfastflow-0.2.8.7.dist-info/WHEEL
mlfastflow-0.2.8.7.dist-info/top_level.txt
mlfastflow-0.2.8.7.dist-info/RECORD
