Metadata-Version: 2.4
Name: mlfastflow
Version: 0.2.8.7
Summary: Packages for fast dataflow and workflow processing
Home-page: https://pypi.org/project/mlfastflow/
Author: Xileven
Author-email: Xileven <hi@bringyouhome.com>
License-Expression: MIT
Project-URL: Documentation, https://github.com/xileven/mlfastflow
Project-URL: Source, https://github.com/xileven/mlfastflow
Project-URL: Tracker, https://github.com/xileven/mlfastflow/issues
Classifier: Development Status :: 3 - Alpha
Classifier: Intended Audience :: Developers
Classifier: Operating System :: OS Independent
Classifier: Programming Language :: Python :: 3.9
Classifier: Programming Language :: Python :: 3.10
Classifier: Programming Language :: Python :: 3.11
Classifier: Programming Language :: Python :: 3.12
Requires-Python: >=3.9
License-File: LICENSE
Requires-Dist: pandas>=1.3.0
Requires-Dist: numpy>=1.20.0
Requires-Dist: google-cloud-bigquery>=3.0.0
Requires-Dist: google-cloud-storage>=2.0.0
Requires-Dist: google-auth>=2.0.0
Requires-Dist: pandas-gbq>=0.17.0
Requires-Dist: pyarrow>=7.0.0
Requires-Dist: python-dotenv>=0.19.0
Requires-Dist: faiss-cpu
Requires-Dist: polars>=1.29.0
Requires-Dist: build>=1.2.2.post1
Requires-Dist: twine>=6.1.0
Requires-Dist: setuptools>=80.4.0
Dynamic: author
Dynamic: home-page
Dynamic: license-file
Dynamic: requires-python
